README.rst
setup.cfg
setup.py
s3_mysql_backup/__init__.py
s3_mysql_backup/backup_db.py
s3_mysql_backup/backup_dir.py
s3_mysql_backup/backup_file.py
s3_mysql_backup/copy_file.py
s3_mysql_backup.egg-info/PKG-INFO
s3_mysql_backup.egg-info/SOURCES.txt
s3_mysql_backup.egg-info/dependency_links.txt
s3_mysql_backup.egg-info/entry_points.txt
s3_mysql_backup.egg-info/requires.txt
s3_mysql_backup.egg-info/top_level.txt
s3_mysql_backup/scripts/__init__.py
s3_mysql_backup/scripts/backup_dir.py
s3_mysql_backup/scripts/backup_gnucash.py
s3_mysql_backup/scripts/backup_qb.py
s3_mysql_backup/scripts/copy_file_to_s3_bucket.py
s3_mysql_backup/scripts/delete_bucket.py
s3_mysql_backup/scripts/get_bucket.py
s3_mysql_backup/scripts/get_bucket_list.py
s3_mysql_backup/scripts/get_dir_backup.py
s3_mysql_backup/test/__init__.py
s3_mysql_backup/test/conftest.py
s3_mysql_backup/test/test_accounting_file_dates.py
s3_mysql_backup/test/test_accounting_file_patterns.py
s3_mysql_backup/test/test_load_modules.py