Metadata-Version: 1.1
Name: s3-mysql-backup
Version: 0.0.36
Summary: Utility Library for Backing up MySQL to S3
Home-page: https://github.com/fogcitymarathoner/s3_mysql_backup
Author: Marc Condon
Author-email: marc@sfgeek.net
License: MIT
Keywords: S3 MySQL fabric
Platform: UNKNOWN
Classifier: Development Status :: 1 - Planning
Classifier: Intended Audience :: Developers
Classifier: Topic :: Utilities
Classifier: License :: OSI Approved :: MIT License
Classifier: Programming Language :: Python :: 2.7
